core_https/__init__.py
core_https/exceptions.py
core_https/py.typed
core_https/utils.py
core_https/requesters/__init__.py
core_https/requesters/aiohttp_.py
core_https/requesters/base.py
core_https/requesters/requests_.py
core_https/requesters/urllib3_.py
core_https/tests/__init__.py
core_https/tests/aiohttp_.py
core_https/tests/base.py
core_https/tests/decorators.py
core_https/tests/requests_.py
core_https/tests/urllib3_.py
core_https-2.0.1.dist-info/licenses/LICENSE
core_https-2.0.1.dist-info/METADATA
core_https-2.0.1.dist-info/WHEEL
core_https-2.0.1.dist-info/top_level.txt
core_https-2.0.1.dist-info/RECORD
